Workbook

Sheet Rules
A1: Helix King Labs — Affiliate mapping
A2: Internal. Program is not live. Settlement v1 is cash only. Last updated 28 Sep 2026.
A4: Order
A5: 1. Customers you can reach today (email list).
A6: 2. Affiliates who already sell this catalog class.
A7: 3. Ads on top of that base.
A8: Operator call note (not a Helix result): 78 sales from people he already knew. 10 already had a code.
A10: Inputs — change the yellow cells
A11: Default commission rate | B11: 0.1 | C11: Assumption only. Set before first partner call.
A12: Cookie window (days) | B12: 30 | C12: Not live. Record the planned window so codes are not issued two ways.
A13: Payout floor (USD) | B13: 50 | C13: Do not pay under this until a real payout batch exists.
A14: Code prefix | B14: HK | C14: Codes read PREFIX-SLUG. Example HK-RYAN.
A15: Self-purchase allowed | B15: No | C15: House rule. Change before launch if you allow it.
A17: Wolverine offer — what partners quote
A18: Public name | B18: Wolverine
A19: Ops SKU | B19: BB20
A20: Fill | B20: BPC-157 10 mg + TB-500 10 mg
A21: Ratio | B21: 1:1
A22: Total peptide | B22: 20 mg
A23: Not offered on this SKU | B23: 5 mg + 5 mg · 20 mg + 20 mg
A24: List price (catalog) | B24: 70 | C24: Signed-in price. No public price guide.
A25: Commission per vial at default rate | B25: =B24*B11 -> 7
A27: Settlement — v1 (use this)
A28: Payout mode | B28: Cash only. Request at $50+. Sweep 31 Dec. | C28: No credit. No multiplier. No micro-payouts.
A29: Year-end sweep | B29: Calendar year (31 Dec) | C29: Pick calendar or fiscal and do not change it mid-year. Calendar is simpler for 1099-NEC.
A30: Minimum cash-out | B30: =B13 -> 50 | C30: Same floor as B13. Below the floor it sits until year-end.
A31: Store credit in v1 | B31: Off — never | C31: Store credit is not a settlement option.
A32: Credit bonus (parked) | B32: 0 | C32: Parked at 0. Do not use.
A34: Worked example — Wolverine BB20
A35: Sale price | B35: =B24 -> 70 | C35: Signed-in catalog price
A36: Cash commission (v1) | B36: =B35*B11 -> 7 | C36: 10% of $70 = $7 per vial
A37: If they refer 3 vials | B37: =B36*3 -> 21 | C37: $21 cash. Below the $50 floor — sits until they request above floor or year-end.
A38: Parked credit on that $21 | B38: =B37*(1+B32) -> 21 | C38: $21 × 1.5 = $31.50. Your $20 → $30 example is the same math.
A39: Effective rate if credit is on | B39: =B11*(1+B32) -> 0.1 | C39: 15% of sale. That is a different program, not a perk on the same 10%.
A41: v1 rule: 10% cash. Pay on request at $50 or more. Sweep leftover on 31 Dec. No store credit. No micro-payouts.
A42: Do not issue a code until the row exists on Roster.

Sheet Roster
A1: Affiliate roster
A2: Yellow = you type. Black = calculated. Status list is locked to the dropdown.
A4: Code | B4: Name | C4: Handle / channel | D4: Audience | E4: Already had a code elsewhere? | F4: Status | G4: Date added | H4: Commission override | I4: Orders | J4: Gross sales (USD) | K4: Commission due | L4: Paid | M4: Balance | N4: Notes
A5: =Rules!$B$14&"-HOUSE" -> HK-HOUSE | B5: Helix King Labs (house) | C5: Owned email list | D5: Customers you can reach today | E5: No | F5: house | G5: 2026-09-28 | H5: 0 | I5: 0 | J5: 0 | K5: 0 | L5: 0 | M5: 0 | N5: House row. Not an affiliate. Do not pay.
A6: =IF(B6="","",Rules!$B$14&"-"&UPPER(LEFT(SUBSTITUTE(B6," ","-"),12))) | E6: No | F6: prospect | K6: =IF(J6="","",ROUND(J6*IF(H6="",Rules!$B$11,H6),2)) | L6: 0 | M6: =IF(K6="","",K6-IF(L6="",0,L6))
A7: =IF(B7="","",Rules!$B$14&"-"&UPPER(LEFT(SUBSTITUTE(B7," ","-"),12))) | E7: No | F7: prospect | K7: =IF(J7="","",ROUND(J7*IF(H7="",Rules!$B$11,H7),2)) | L7: 0 | M7: =IF(K7="","",K7-IF(L7="",0,L7))
A8: =IF(B8="","",Rules!$B$14&"-"&UPPER(LEFT(SUBSTITUTE(B8," ","-"),12))) | E8: No | F8: prospect | K8: =IF(J8="","",ROUND(J8*IF(H8="",Rules!$B$11,H8),2)) | L8: 0 | M8: =IF(K8="","",K8-IF(L8="",0,L8))
A9: =IF(B9="","",Rules!$B$14&"-"&UPPER(LEFT(SUBSTITUTE(B9," ","-"),12))) | E9: No | F9: prospect | K9: =IF(J9="","",ROUND(J9*IF(H9="",Rules!$B$11,H9),2)) | L9: 0 | M9: =IF(K9="","",K9-IF(L9="",0,L9))
A10: =IF(B10="","",Rules!$B$14&"-"&UPPER(LEFT(SUBSTITUTE(B10," ","-"),12))) | E10: No | F10: prospect | K10: =IF(J10="","",ROUND(J10*IF(H10="",Rules!$B$11,H10),2)) | L10: 0 | M10: =IF(K10="","",K10-IF(L10="",0,L10))
A11: =IF(B11="","",Rules!$B$14&"-"&UPPER(LEFT(SUBSTITUTE(B11," ","-"),12))) | E11: No | F11: prospect | K11: =IF(J11="","",ROUND(J11*IF(H11="",Rules!$B$11,H11),2)) | L11: 0 | M11: =IF(K11="","",K11-IF(L11="",0,L11))
A12: =IF(B12="","",Rules!$B$14&"-"&UPPER(LEFT(SUBSTITUTE(B12," ","-"),12))) | E12: No | F12: prospect | K12: =IF(J12="","",ROUND(J12*IF(H12="",Rules!$B$11,H12),2)) | L12: 0 | M12: =IF(K12="","",K12-IF(L12="",0,L12))
A13: =IF(B13="","",Rules!$B$14&"-"&UPPER(LEFT(SUBSTITUTE(B13," ","-"),12))) | E13: No | F13: prospect | K13: =IF(J13="","",ROUND(J13*IF(H13="",Rules!$B$11,H13),2)) | L13: 0 | M13: =IF(K13="","",K13-IF(L13="",0,L13))
A14: =IF(B14="","",Rules!$B$14&"-"&UPPER(LEFT(SUBSTITUTE(B14," ","-"),12))) | E14: No | F14: prospect | K14: =IF(J14="","",ROUND(J14*IF(H14="",Rules!$B$11,H14),2)) | L14: 0 | M14: =IF(K14="","",K14-IF(L14="",0,L14))
A15: =IF(B15="","",Rules!$B$14&"-"&UPPER(LEFT(SUBSTITUTE(B15," ","-"),12))) | E15: No | F15: prospect | K15: =IF(J15="","",ROUND(J15*IF(H15="",Rules!$B$11,H15),2)) | L15: 0 | M15: =IF(K15="","",K15-IF(L15="",0,L15))
A16: =IF(B16="","",Rules!$B$14&"-"&UPPER(LEFT(SUBSTITUTE(B16," ","-"),12))) | E16: No | F16: prospect | K16: =IF(J16="","",ROUND(J16*IF(H16="",Rules!$B$11,H16),2)) | L16: 0 | M16: =IF(K16="","",K16-IF(L16="",0,L16))
A17: =IF(B17="","",Rules!$B$14&"-"&UPPER(LEFT(SUBSTITUTE(B17," ","-"),12))) | E17: No | F17: prospect | K17: =IF(J17="","",ROUND(J17*IF(H17="",Rules!$B$11,H17),2)) | L17: 0 | M17: =IF(K17="","",K17-IF(L17="",0,L17))
... A24: =IF(B24="","",Rules!$B$14&"-"&UPPER(LEFT(SUBSTITUTE(B24," ","-"),12))) | E24: No | F24: prospect | K24: =IF(J24="","",ROUND(J24*IF(H24="",Rules!$B$11,H24),2)) | L24: 0 | M24: =IF(K24="","",K24-IF(L24="",0,L24))
A26: Totals | I26: =SUM(I6:I24) -> 0 | J26: =SUM(J6:J24) -> 0 | K26: =SUM(K6:K24) -> 0 | L26: =SUM(L6:L24) -> 0 | M26: =SUM(M6:M24) -> 0
A28: Count with a name | B28: =COUNTA(B6:B24) -> 0
A29: Active | B29: =COUNTIF(F6:F24,"active") -> 0
A30: Already had a code elsewhere | B30: =COUNTIF(E6:E24,"Yes") -> 0
A31: Payable now (balance ≥ floor) | B31: =COUNTIFS(M6:M24,">="&Rules!$B$13,F6:F24,"active") -> 0

Sheet This week
A1: This week — names you can reach
A2: Write the first ten people before you design a landing page. Codes generate on Roster when you type a name.
A4: # | B4: Name | C4: How you know them | D4: What they already sell | E4: Ask this week | F4: Done
A5: 1
A6: 2
A7: 3
A8: 4
A9: 5
A10: 6
A11: 7
A12: 8
A13: 9
A14: 10
A16: Asked this week | B16: =COUNTIF(F5:F14,"Yes") -> 0
A17: Still open | B17: =COUNTA(B5:B14)-B16 -> 0

Sheet Quote sheet
A1: What an affiliate is allowed to say
A2: No protocols. No outcome claims. Name, fill, form, lot. Research use on documented compounds.
A4: Public name | B4: SKU | C4: Fill / form | D4: Line they can send
A5: Wolverine | B5: BB20 | C5: BPC-157 10 mg + TB-500 10 mg · lyophilized vial · 1:1 · 20 mg total | D5: Wolverine. BPC-157 10 mg + TB-500 10 mg in one vial. Research use only.
A6: PGL-GIC1 | B6: RT10 / RT20 / RT30 | C6: 10 / 20 / 30 mg · lyophilized vial | D6: PGL-GIC1. Strength on the card. Research use only.
A7: PGL-GI1 | B7: TR10 / TR20 / TR30 | C7: 10 / 20 / 30 mg · lyophilized vial | D7: PGL-GI1. Strength on the card. Research use only.
A8: Tesamorelin | B8: TSM10 / TSM20 | C8: 10 / 20 mg · lyophilized vial | D8: Tesamorelin. Strength on the card. Research use only.
A9: Selank | B9: SEL10 | C9: 10 mg / 10 mL nasal spray | D9: Selank nasal spray. 10 mg / 10 mL. Research use only.
A10: Semax | B10: SMX10 | C10: 10 mg / 10 mL nasal spray | D10: Semax nasal spray. 10 mg / 10 mL. Research use only.
A11: T2.5 Bio-Tallow | B11: T25 | C11: 60 mL cosmetic jar | D11: T2.5 GHK-infused bio-tallow. Cosmetic lot.
